{"id":"3Y2u","dependencies":[{"name":"/home/max/Desktop/BlockByBlock/Projects/BlockByBlock/node_modules/ol/package.json","includedInParent":true,"mtime":1537270483857},{"name":"/home/max/Desktop/BlockByBlock/Projects/BlockByBlock/package.json","includedInParent":true,"mtime":1537270485797},{"name":"../ImageCanvas.js","loc":{"line":5,"column":24},"parent":"/home/max/Desktop/BlockByBlock/Projects/BlockByBlock/node_modules/ol/source/ImageCanvas.js","resolved":"/home/max/Desktop/BlockByBlock/Projects/BlockByBlock/node_modules/ol/ImageCanvas.js"},{"name":"../extent.js","loc":{"line":6,"column":67},"parent":"/home/max/Desktop/BlockByBlock/Projects/BlockByBlock/node_modules/ol/source/ImageCanvas.js","resolved":"/home/max/Desktop/BlockByBlock/Projects/BlockByBlock/node_modules/ol/extent.js"},{"name":"../source/Image.js","loc":{"line":7,"column":24},"parent":"/home/max/Desktop/BlockByBlock/Projects/BlockByBlock/node_modules/ol/source/ImageCanvas.js","resolved":"/home/max/Desktop/BlockByBlock/Projects/BlockByBlock/node_modules/ol/source/Image.js"}],"generated":{"js":"\"use strict\";Object.defineProperty(exports,\"__esModule\",{value:!0});var t=require(\"../ImageCanvas.js\"),e=r(t),i=require(\"../extent.js\"),n=require(\"../source/Image.js\"),o=r(n);function r(t){return t&&t.__esModule?t:{default:t}}var s=function(t){function n(e){t.call(this,{attributions:e.attributions,projection:e.projection,resolutions:e.resolutions,state:e.state}),this.canvasFunction_=e.canvasFunction,this.canvas_=null,this.renderedRevision_=0,this.ratio_=void 0!==e.ratio?e.ratio:1.5}return t&&(n.__proto__=t),n.prototype=Object.create(t&&t.prototype),n.prototype.constructor=n,n.prototype.getImageInternal=function(t,n,o,r){n=this.findNearestResolution(n);var s=this.canvas_;if(s&&this.renderedRevision_==this.getRevision()&&s.getResolution()==n&&s.getPixelRatio()==o&&(0,i.containsExtent)(s.getExtent(),t))return s;t=t.slice(),(0,i.scaleFromCenter)(t,this.ratio_);var a=[(0,i.getWidth)(t)/n*o,(0,i.getHeight)(t)/n*o],u=this.canvasFunction_(t,n,o,a,r);return u&&(s=new e.default(t,n,o,u)),this.canvas_=s,this.renderedRevision_=this.getRevision(),s},n}(o.default);exports.default=s;","map":{"mappings":[{"source":"node_modules/ol/source/ImageCanvas.js","original":{"line":129,"column":0},"generated":{"line":1,"column":0}},{"source":"node_modules/ol/source/ImageCanvas.js","original":{"line":129,"column":0},"generated":{"line":1,"column":13}},{"source":"node_modules/ol/source/ImageCanvas.js","original":{"line":129,"column":0},"generated":{"line":1,"column":20}},{"source":"node_modules/ol/source/ImageCanvas.js","original":{"line":129,"column":0},"generated":{"line":1,"column":35}},{"source":"node_modules/ol/source/ImageCanvas.js","original":{"line":129,"column":0},"generated":{"line":1,"column":43}},{"source":"node_modules/ol/source/ImageCanvas.js","original":{"line":129,"column":0},"generated":{"line":1,"column":56}},{"source":"node_modules/ol/source/ImageCanvas.js","original":{"line":129,"column":0},"generated":{"line":1,"column":57}},{"source":"node_modules/ol/source/ImageCanvas.js","original":{"line":129,"column":0},"generated":{"line":1,"column":64}},{"source":"node_modules/ol/source/ImageCanvas.js","original":{"line":5,"column":0},"generated":{"line":1,"column":68}},{"source":"node_modules/ol/source/ImageCanvas.js","original":{"line":5,"column":0},"generated":{"line":1,"column":72}},{"source":"node_modules/ol/source/ImageCanvas.js","original":{"line":5,"column":0},"generated":{"line":1,"column":74}},{"source":"node_modules/ol/source/ImageCanvas.js","original":{"line":5,"column":0},"generated":{"line":1,"column":82}},{"source":"node_modules/ol/source/ImageCanvas.js","original":{"line":129,"column":0},"generated":{"line":1,"column":103}},{"source":"node_modules/ol/source/ImageCanvas.js","original":{"line":129,"column":0},"generated":{"line":1,"column":105}},{"source":"node_modules/ol/source/ImageCanvas.js","original":{"line":129,"column":0},"generated":{"line":1,"column":107}},{"source":"node_modules/ol/source/ImageCanvas.js","original":{"line":6,"column":0},"generated":{"line":1,"column":110}},{"source":"node_modules/ol/source/ImageCanvas.js","original":{"line":6,"column":0},"generated":{"line":1,"column":112}},{"source":"node_modules/ol/source/ImageCanvas.js","original":{"line":6,"column":0},"generated":{"line":1,"column":120}},{"source":"node_modules/ol/source/ImageCanvas.js","original":{"line":7,"column":0},"generated":{"line":1,"column":136}},{"source":"node_modules/ol/source/ImageCanvas.js","original":{"line":7,"column":0},"generated":{"line":1,"column":138}},{"source":"node_modules/ol/source/ImageCanvas.js","original":{"line":7,"column":0},"generated":{"line":1,"column":146}},{"source":"node_modules/ol/source/ImageCanvas.js","original":{"line":129,"column":0},"generated":{"line":1,"column":168}},{"source":"node_modules/ol/source/ImageCanvas.js","original":{"line":129,"column":0},"generated":{"line":1,"column":170}},{"source":"node_modules/ol/source/ImageCanvas.js","original":{"line":129,"column":0},"generated":{"line":1,"column":172}},{"source":"node_modules/ol/source/ImageCanvas.js","original":{"line":129,"column":0},"generated":{"line":1,"column":175}},{"source":"node_modules/ol/source/ImageCanvas.js","original":{"line":129,"column":0},"generated":{"line":1,"column":184}},{"source":"node_modules/ol/source/ImageCanvas.js","original":{"line":129,"column":0},"generated":{"line":1,"column":186}},{"source":"node_modules/ol/source/ImageCanvas.js","original":{"line":129,"column":0},"generated":{"line":1,"column":189}},{"source":"node_modules/ol/source/ImageCanvas.js","original":{"line":129,"column":0},"generated":{"line":1,"column":196}},{"source":"node_modules/ol/source/ImageCanvas.js","original":{"line":129,"column":0},"generated":{"line":1,"column":199}},{"source":"node_modules/ol/source/ImageCanvas.js","original":{"line":129,"column":0},"generated":{"line":1,"column":201}},{"source":"node_modules/ol/source/ImageCanvas.js","original":{"line":129,"column":0},"generated":{"line":1,"column":212}},{"source":"node_modules/ol/source/ImageCanvas.js","original":{"line":129,"column":0},"generated":{"line":1,"column":214}},{"source":"node_modules/ol/source/ImageCanvas.js","original":{"line":129,"column":0},"generated":{"line":1,"column":215}},{"source":"node_modules/ol/source/ImageCanvas.js","original":{"line":129,"column":0},"generated":{"line":1,"column":223}},{"source":"node_modules/ol/source/ImageCanvas.js","original":{"line":50,"column":0},"generated":{"line":1,"column":226}},{"source":"node_modules/ol/source/ImageCanvas.js","name":"ImageCanvasSource","original":{"line":50,"column":4},"generated":{"line":1,"column":230}},{"source":"node_modules/ol/source/ImageCanvas.js","original":{"line":50,"column":25},"generated":{"line":1,"column":232}},{"source":"node_modules/ol/source/ImageCanvas.js","name":"ImageSource","original":{"line":50,"column":35},"generated":{"line":1,"column":241}},{"source":"node_modules/ol/source/ImageCanvas.js","name":"ImageCanvasSource","original":{"line":51,"column":11},"generated":{"line":1,"column":244}},{"source":"node_modules/ol/source/ImageCanvas.js","name":"ImageCanvasSource","original":{"line":51,"column":11},"generated":{"line":1,"column":253}},{"source":"node_modules/ol/source/ImageCanvas.js","name":"options","original":{"line":51,"column":29},"generated":{"line":1,"column":255}},{"source":"node_modules/ol/source/ImageCanvas.js","name":"call","original":{"line":53,"column":16},"generated":{"line":1,"column":258}},{"source":"node_modules/ol/source/ImageCanvas.js","name":"call","original":{"line":53,"column":16},"generated":{"line":1,"column":260}},{"source":"node_modules/ol/source/ImageCanvas.js","original":{"line":53,"column":21},"generated":{"line":1,"column":265}},{"source":"node_modules/ol/source/ImageCanvas.js","original":{"line":53,"column":27},"generated":{"line":1,"column":270}},{"source":"node_modules/ol/source/ImageCanvas.js","name":"options","original":{"line":54,"column":20},"generated":{"line":1,"column":271}},{"source":"node_modules/ol/source/ImageCanvas.js","name":"options","original":{"line":54,"column":20},"generated":{"line":1,"column":284}},{"source":"node_modules/ol/source/ImageCanvas.js","name":"attributions","original":{"line":54,"column":28},"generated":{"line":1,"column":286}},{"source":"node_modules/ol/source/ImageCanvas.js","name":"options","original":{"line":55,"column":18},"generated":{"line":1,"column":299}},{"source":"node_modules/ol/source/ImageCanvas.js","name":"options","original":{"line":55,"column":18},"generated":{"line":1,"column":310}},{"source":"node_modules/ol/source/ImageCanvas.js","name":"projection","original":{"line":55,"column":26},"generated":{"line":1,"column":312}},{"source":"node_modules/ol/source/ImageCanvas.js","name":"options","original":{"line":56,"column":19},"generated":{"line":1,"column":323}},{"source":"node_modules/ol/source/ImageCanvas.js","name":"options","original":{"line":56,"column":19},"generated":{"line":1,"column":335}},{"source":"node_modules/ol/source/ImageCanvas.js","name":"resolutions","original":{"line":56,"column":27},"generated":{"line":1,"column":337}},{"source":"node_modules/ol/source/ImageCanvas.js","name":"options","original":{"line":57,"column":13},"generated":{"line":1,"column":349}},{"source":"node_modules/ol/source/ImageCanvas.js","name":"options","original":{"line":57,"column":13},"generated":{"line":1,"column":355}},{"source":"node_modules/ol/source/ImageCanvas.js","name":"state","original":{"line":57,"column":21},"generated":{"line":1,"column":357}},{"source":"node_modules/ol/source/ImageCanvas.js","name":"canvasFunction_","original":{"line":64,"column":9},"generated":{"line":1,"column":365}},{"source":"node_modules/ol/source/ImageCanvas.js","name":"canvasFunction_","original":{"line":64,"column":9},"generated":{"line":1,"column":370}},{"source":"node_modules/ol/source/ImageCanvas.js","name":"options","original":{"line":64,"column":27},"generated":{"line":1,"column":386}},{"source":"node_modules/ol/source/ImageCanvas.js","name":"canvasFunction","original":{"line":64,"column":35},"generated":{"line":1,"column":388}},{"source":"node_modules/ol/source/ImageCanvas.js","name":"canvas_","original":{"line":70,"column":9},"generated":{"line":1,"column":403}},{"source":"node_modules/ol/source/ImageCanvas.js","name":"canvas_","original":{"line":70,"column":9},"generated":{"line":1,"column":408}},{"source":"node_modules/ol/source/ImageCanvas.js","original":{"line":70,"column":19},"generated":{"line":1,"column":416}},{"source":"node_modules/ol/source/ImageCanvas.js","name":"renderedRevision_","original":{"line":76,"column":9},"generated":{"line":1,"column":421}},{"source":"node_modules/ol/source/ImageCanvas.js","name":"renderedRevision_","original":{"line":76,"column":9},"generated":{"line":1,"column":426}},{"source":"node_modules/ol/source/ImageCanvas.js","original":{"line":76,"column":29},"generated":{"line":1,"column":444}},{"source":"node_modules/ol/source/ImageCanvas.js","name":"ratio_","original":{"line":82,"column":9},"generated":{"line":1,"column":446}},{"source":"node_modules/ol/source/ImageCanvas.js","name":"ratio_","original":{"line":82,"column":9},"generated":{"line":1,"column":451}},{"source":"node_modules/ol/source/ImageCanvas.js","name":"undefined","original":{"line":82,"column":36},"generated":{"line":1,"column":463}},{"source":"node_modules/ol/source/ImageCanvas.js","name":"options","original":{"line":82,"column":18},"generated":{"line":1,"column":467}},{"source":"node_modules/ol/source/ImageCanvas.js","name":"ratio","original":{"line":82,"column":26},"generated":{"line":1,"column":469}},{"source":"node_modules/ol/source/ImageCanvas.js","name":"options","original":{"line":83,"column":6},"generated":{"line":1,"column":475}},{"source":"node_modules/ol/source/ImageCanvas.js","name":"ratio","original":{"line":83,"column":14},"generated":{"line":1,"column":477}},{"source":"node_modules/ol/source/ImageCanvas.js","original":{"line":83,"column":22},"generated":{"line":1,"column":483}},{"source":"node_modules/ol/source/ImageCanvas.js","name":"ImageCanvasSource","original":{"line":123,"column":9},"generated":{"line":1,"column":487}},{"source":"node_modules/ol/source/ImageCanvas.js","name":"ImageSource","original":{"line":87,"column":7},"generated":{"line":1,"column":494}},{"source":"node_modules/ol/source/ImageCanvas.js","name":"ImageCanvasSource","original":{"line":87,"column":21},"generated":{"line":1,"column":498}},{"source":"node_modules/ol/source/ImageCanvas.js","name":"__proto__","original":{"line":87,"column":39},"generated":{"line":1,"column":500}},{"source":"node_modules/ol/source/ImageCanvas.js","name":"ImageSource","original":{"line":87,"column":51},"generated":{"line":1,"column":510}},{"source":"node_modules/ol/source/ImageCanvas.js","name":"prototype","original":{"line":88,"column":20},"generated":{"line":1,"column":513}},{"source":"node_modules/ol/source/ImageCanvas.js","name":"prototype","original":{"line":88,"column":20},"generated":{"line":1,"column":515}},{"source":"node_modules/ol/source/ImageCanvas.js","name":"Object","original":{"line":88,"column":32},"generated":{"line":1,"column":525}},{"source":"node_modules/ol/source/ImageCanvas.js","name":"create","original":{"line":88,"column":39},"generated":{"line":1,"column":532}},{"source":"node_modules/ol/source/ImageCanvas.js","name":"ImageSource","original":{"line":88,"column":47},"generated":{"line":1,"column":539}},{"source":"node_modules/ol/source/ImageCanvas.js","name":"ImageSource","original":{"line":88,"column":62},"generated":{"line":1,"column":542}},{"source":"node_modules/ol/source/ImageCanvas.js","name":"prototype","original":{"line":88,"column":74},"generated":{"line":1,"column":544}},{"source":"node_modules/ol/source/ImageCanvas.js","name":"prototype","original":{"line":89,"column":20},"generated":{"line":1,"column":555}},{"source":"node_modules/ol/source/ImageCanvas.js","name":"prototype","original":{"line":89,"column":20},"generated":{"line":1,"column":557}},{"source":"node_modules/ol/source/ImageCanvas.js","name":"constructor","original":{"line":89,"column":30},"generated":{"line":1,"column":567}},{"source":"node_modules/ol/source/ImageCanvas.js","name":"ImageCanvasSource","original":{"line":89,"column":44},"generated":{"line":1,"column":579}},{"source":"node_modules/ol/source/ImageCanvas.js","name":"prototype","original":{"line":94,"column":20},"generated":{"line":1,"column":581}},{"source":"node_modules/ol/source/ImageCanvas.js","name":"prototype","original":{"line":94,"column":20},"generated":{"line":1,"column":583}},{"source":"node_modules/ol/source/ImageCanvas.js","name":"getImageInternal","original":{"line":94,"column":30},"generated":{"line":1,"column":593}},{"source":"node_modules/ol/source/ImageCanvas.js","original":{"line":94,"column":49},"generated":{"line":1,"column":610}},{"source":"node_modules/ol/source/ImageCanvas.js","name":"extent","original":{"line":94,"column":76},"generated":{"line":1,"column":619}},{"source":"node_modules/ol/source/ImageCanvas.js","name":"resolution","original":{"line":94,"column":84},"generated":{"line":1,"column":621}},{"source":"node_modules/ol/source/ImageCanvas.js","name":"pixelRatio","original":{"line":94,"column":96},"generated":{"line":1,"column":623}},{"source":"node_modules/ol/source/ImageCanvas.js","name":"projection","original":{"line":94,"column":108},"generated":{"line":1,"column":625}},{"source":"node_modules/ol/source/ImageCanvas.js","original":{"line":95,"column":17},"generated":{"line":1,"column":628}},{"source":"node_modules/ol/source/ImageCanvas.js","original":{"line":95,"column":17},"generated":{"line":1,"column":630}},{"source":"node_modules/ol/source/ImageCanvas.js","name":"findNearestResolution","original":{"line":95,"column":22},"generated":{"line":1,"column":635}},{"source":"node_modules/ol/source/ImageCanvas.js","name":"resolution","original":{"line":95,"column":44},"generated":{"line":1,"column":657}},{"source":"node_modules/ol/source/ImageCanvas.js","name":"canvas","original":{"line":97,"column":8},"generated":{"line":1,"column":660}},{"source":"node_modules/ol/source/ImageCanvas.js","name":"canvas","original":{"line":97,"column":8},"generated":{"line":1,"column":664}},{"source":"node_modules/ol/source/ImageCanvas.js","original":{"line":97,"column":17},"generated":{"line":1,"column":666}},{"source":"node_modules/ol/source/ImageCanvas.js","name":"canvas_","original":{"line":97,"column":22},"generated":{"line":1,"column":671}},{"source":"node_modules/ol/source/ImageCanvas.js","name":"canvas","original":{"line":98,"column":8},"generated":{"line":1,"column":679}},{"source":"node_modules/ol/source/ImageCanvas.js","name":"canvas","original":{"line":98,"column":8},"generated":{"line":1,"column":682}},{"source":"node_modules/ol/source/ImageCanvas.js","original":{"line":99,"column":7},"generated":{"line":1,"column":685}},{"source":"node_modules/ol/source/ImageCanvas.js","name":"renderedRevision_","original":{"line":99,"column":12},"generated":{"line":1,"column":690}},{"source":"node_modules/ol/source/ImageCanvas.js","original":{"line":99,"column":33},"generated":{"line":1,"column":709}},{"source":"node_modules/ol/source/ImageCanvas.js","name":"getRevision","original":{"line":99,"column":38},"generated":{"line":1,"column":714}},{"source":"node_modules/ol/source/ImageCanvas.js","name":"canvas","original":{"line":100,"column":7},"generated":{"line":1,"column":729}},{"source":"node_modules/ol/source/ImageCanvas.js","name":"getResolution","original":{"line":100,"column":14},"generated":{"line":1,"column":731}},{"source":"node_modules/ol/source/ImageCanvas.js","name":"resolution","original":{"line":100,"column":33},"generated":{"line":1,"column":748}},{"source":"node_modules/ol/source/ImageCanvas.js","name":"canvas","original":{"line":101,"column":7},"generated":{"line":1,"column":751}},{"source":"node_modules/ol/source/ImageCanvas.js","name":"getPixelRatio","original":{"line":101,"column":14},"generated":{"line":1,"column":753}},{"source":"node_modules/ol/source/ImageCanvas.js","name":"pixelRatio","original":{"line":101,"column":33},"generated":{"line":1,"column":770}},{"source":"node_modules/ol/source/ImageCanvas.js","original":{"line":102,"column":7},"generated":{"line":1,"column":774}},{"source":"node_modules/ol/source/ImageCanvas.js","name":"canvas","original":{"line":102,"column":22},"generated":{"line":1,"column":776}},{"source":"node_modules/ol/source/ImageCanvas.js","name":"canvas","original":{"line":102,"column":22},"generated":{"line":1,"column":778}},{"source":"node_modules/ol/source/ImageCanvas.js","name":"canvas","original":{"line":102,"column":22},"generated":{"line":1,"column":794}},{"source":"node_modules/ol/source/ImageCanvas.js","name":"getExtent","original":{"line":102,"column":29},"generated":{"line":1,"column":796}},{"source":"node_modules/ol/source/ImageCanvas.js","name":"extent","original":{"line":102,"column":42},"generated":{"line":1,"column":808}},{"source":"node_modules/ol/source/ImageCanvas.js","name":"canvas","original":{"line":103,"column":13},"generated":{"line":1,"column":811}},{"source":"node_modules/ol/source/ImageCanvas.js","name":"canvas","original":{"line":103,"column":13},"generated":{"line":1,"column":818}},{"source":"node_modules/ol/source/ImageCanvas.js","name":"extent","original":{"line":106,"column":13},"generated":{"line":1,"column":820}},{"source":"node_modules/ol/source/ImageCanvas.js","name":"extent","original":{"line":106,"column":13},"generated":{"line":1,"column":822}},{"source":"node_modules/ol/source/ImageCanvas.js","name":"slice","original":{"line":106,"column":20},"generated":{"line":1,"column":824}},{"source":"node_modules/ol/source/ImageCanvas.js","name":"extent","original":{"line":107,"column":20},"generated":{"line":1,"column":833}},{"source":"node_modules/ol/source/ImageCanvas.js","name":"extent","original":{"line":107,"column":20},"generated":{"line":1,"column":835}},{"source":"node_modules/ol/source/ImageCanvas.js","name":"extent","original":{"line":107,"column":20},"generated":{"line":1,"column":837}},{"source":"node_modules/ol/source/ImageCanvas.js","name":"extent","original":{"line":107,"column":20},"generated":{"line":1,"column":854}},{"source":"node_modules/ol/source/ImageCanvas.js","original":{"line":107,"column":28},"generated":{"line":1,"column":856}},{"source":"node_modules/ol/source/ImageCanvas.js","name":"ratio_","original":{"line":107,"column":33},"generated":{"line":1,"column":861}},{"source":"node_modules/ol/source/ImageCanvas.js","name":"width","original":{"line":108,"column":8},"generated":{"line":1,"column":869}},{"source":"node_modules/ol/source/ImageCanvas.js","name":"size","original":{"line":110,"column":8},"generated":{"line":1,"column":873}},{"source":"node_modules/ol/source/ImageCanvas.js","original":{"line":110,"column":15},"generated":{"line":1,"column":875}},{"source":"node_modules/ol/source/ImageCanvas.js","original":{"line":108,"column":16},"generated":{"line":1,"column":877}},{"source":"node_modules/ol/source/ImageCanvas.js","name":"extent","original":{"line":108,"column":25},"generated":{"line":1,"column":879}},{"source":"node_modules/ol/source/ImageCanvas.js","name":"extent","original":{"line":108,"column":25},"generated":{"line":1,"column":881}},{"source":"node_modules/ol/source/ImageCanvas.js","name":"extent","original":{"line":108,"column":25},"generated":{"line":1,"column":891}},{"source":"node_modules/ol/source/ImageCanvas.js","name":"resolution","original":{"line":108,"column":35},"generated":{"line":1,"column":894}},{"source":"node_modules/ol/source/ImageCanvas.js","name":"pixelRatio","original":{"line":110,"column":24},"generated":{"line":1,"column":896}},{"source":"node_modules/ol/source/ImageCanvas.js","original":{"line":109,"column":17},"generated":{"line":1,"column":899}},{"source":"node_modules/ol/source/ImageCanvas.js","name":"extent","original":{"line":109,"column":27},"generated":{"line":1,"column":901}},{"source":"node_modules/ol/source/ImageCanvas.js","name":"extent","original":{"line":109,"column":27},"generated":{"line":1,"column":903}},{"source":"node_modules/ol/source/ImageCanvas.js","name":"extent","original":{"line":109,"column":27},"generated":{"line":1,"column":914}},{"source":"node_modules/ol/source/ImageCanvas.js","name":"resolution","original":{"line":109,"column":37},"generated":{"line":1,"column":917}},{"source":"node_modules/ol/source/ImageCanvas.js","name":"pixelRatio","original":{"line":110,"column":45},"generated":{"line":1,"column":919}},{"source":"node_modules/ol/source/ImageCanvas.js","name":"canvasElement","original":{"line":112,"column":8},"generated":{"line":1,"column":922}},{"source":"node_modules/ol/source/ImageCanvas.js","original":{"line":112,"column":24},"generated":{"line":1,"column":924}},{"source":"node_modules/ol/source/ImageCanvas.js","name":"canvasFunction_","original":{"line":112,"column":29},"generated":{"line":1,"column":929}},{"source":"node_modules/ol/source/ImageCanvas.js","name":"extent","original":{"line":113,"column":6},"generated":{"line":1,"column":945}},{"source":"node_modules/ol/source/ImageCanvas.js","name":"resolution","original":{"line":113,"column":14},"generated":{"line":1,"column":947}},{"source":"node_modules/ol/source/ImageCanvas.js","name":"pixelRatio","original":{"line":113,"column":26},"generated":{"line":1,"column":949}},{"source":"node_modules/ol/source/ImageCanvas.js","name":"size","original":{"line":113,"column":38},"generated":{"line":1,"column":951}},{"source":"node_modules/ol/source/ImageCanvas.js","name":"projection","original":{"line":113,"column":44},"generated":{"line":1,"column":953}},{"source":"node_modules/ol/source/ImageCanvas.js","name":"canvas","original":{"line":120,"column":11},"generated":{"line":1,"column":956}},{"source":"node_modules/ol/source/ImageCanvas.js","name":"canvasElement","original":{"line":114,"column":8},"generated":{"line":1,"column":963}},{"source":"node_modules/ol/source/ImageCanvas.js","original":{"line":115,"column":15},"generated":{"line":1,"column":967}},{"source":"node_modules/ol/source/ImageCanvas.js","original":{"line":115,"column":15},"generated":{"line":1,"column":969}},{"source":"node_modules/ol/source/ImageCanvas.js","name":"ImageCanvas","original":{"line":115,"column":19},"generated":{"line":1,"column":973}},{"source":"node_modules/ol/source/ImageCanvas.js","original":{"line":115,"column":15},"generated":{"line":1,"column":975}},{"source":"node_modules/ol/source/ImageCanvas.js","name":"extent","original":{"line":115,"column":31},"generated":{"line":1,"column":983}},{"source":"node_modules/ol/source/ImageCanvas.js","name":"resolution","original":{"line":115,"column":39},"generated":{"line":1,"column":985}},{"source":"node_modules/ol/source/ImageCanvas.js","name":"pixelRatio","original":{"line":115,"column":51},"generated":{"line":1,"column":987}},{"source":"node_modules/ol/source/ImageCanvas.js","name":"canvasElement","original":{"line":115,"column":63},"generated":{"line":1,"column":989}},{"source":"node_modules/ol/source/ImageCanvas.js","name":"canvas_","original":{"line":117,"column":9},"generated":{"line":1,"column":993}},{"source":"node_modules/ol/source/ImageCanvas.js","name":"canvas_","original":{"line":117,"column":9},"generated":{"line":1,"column":998}},{"source":"node_modules/ol/source/ImageCanvas.js","name":"canvas","original":{"line":117,"column":19},"generated":{"line":1,"column":1006}},{"source":"node_modules/ol/source/ImageCanvas.js","name":"renderedRevision_","original":{"line":118,"column":9},"generated":{"line":1,"column":1008}},{"source":"node_modules/ol/source/ImageCanvas.js","name":"renderedRevision_","original":{"line":118,"column":9},"generated":{"line":1,"column":1013}},{"source":"node_modules/ol/source/ImageCanvas.js","original":{"line":118,"column":29},"generated":{"line":1,"column":1031}},{"source":"node_modules/ol/source/ImageCanvas.js","name":"getRevision","original":{"line":118,"column":34},"generated":{"line":1,"column":1036}},{"source":"node_modules/ol/source/ImageCanvas.js","name":"canvas","original":{"line":120,"column":11},"generated":{"line":1,"column":1050}},{"source":"node_modules/ol/source/ImageCanvas.js","name":"ImageCanvasSource","original":{"line":123,"column":9},"generated":{"line":1,"column":1053}},{"source":"node_modules/ol/source/ImageCanvas.js","original":{"line":50,"column":25},"generated":{"line":1,"column":1055}},{"source":"node_modules/ol/source/ImageCanvas.js","name":"ImageSource","original":{"line":124,"column":2},"generated":{"line":1,"column":1056}},{"source":"node_modules/ol/source/ImageCanvas.js","original":{"line":50,"column":25},"generated":{"line":1,"column":1058}},{"source":"node_modules/ol/source/ImageCanvas.js","name":"ImageCanvasSource","original":{"line":127,"column":15},"generated":{"line":1,"column":1067}},{"source":"node_modules/ol/source/ImageCanvas.js","name":"ImageCanvasSource","original":{"line":127,"column":15},"generated":{"line":1,"column":1075}},{"source":"node_modules/ol/source/ImageCanvas.js","name":"ImageCanvasSource","original":{"line":127,"column":15},"generated":{"line":1,"column":1083}}],"sources":{"node_modules/ol/source/ImageCanvas.js":"/**\n * @module ol/source/ImageCanvas\n */\n\nimport ImageCanvas from '../ImageCanvas.js';\nimport {containsExtent, getHeight, getWidth, scaleFromCenter} from '../extent.js';\nimport ImageSource from '../source/Image.js';\n\n\n/**\n * A function returning the canvas element (`{HTMLCanvasElement}`)\n * used by the source as an image. The arguments passed to the function are:\n * {@link module:ol/extent~Extent} the image extent, `{number}` the image resolution,\n * `{number}` the device pixel ratio, {@link module:ol/size~Size} the image size, and\n * {@link module:ol/proj/Projection} the image projection. The canvas returned by\n * this function is cached by the source. The this keyword inside the function\n * references the {@link module:ol/source/ImageCanvas}.\n *\n * @typedef {function(this:module:ol/ImageCanvas, module:ol/extent~Extent, number,\n *     number, module:ol/size~Size, module:ol/proj/Projection): HTMLCanvasElement} FunctionType\n */\n\n\n/**\n * @typedef {Object} Options\n * @property {module:ol/source/Source~AttributionLike} [attributions] Attributions.\n * @property {module:ol/source/ImageCanvas~FunctionType} [canvasFunction] Canvas function.\n * The function returning the canvas element used by the source\n * as an image. The arguments passed to the function are: `{module:ol/extent~Extent}` the\n * image extent, `{number}` the image resolution, `{number}` the device pixel\n * ratio, `{module:ol/size~Size}` the image size, and `{module:ol/proj/Projection~Projection}` the image\n * projection. The canvas returned by this function is cached by the source. If\n * the value returned by the function is later changed then\n * `changed` should be called on the source for the source to\n * invalidate the current cached image. See @link: {@link module:ol/Observable~Observable#changed}\n * @property {module:ol/proj~ProjectionLike} projection Projection.\n * @property {number} [ratio=1.5] Ratio. 1 means canvases are the size of the map viewport, 2 means twice the\n * width and height of the map viewport, and so on. Must be `1` or higher.\n * @property {Array<number>} [resolutions] Resolutions.\n * If specified, new canvases will be created for these resolutions\n * @property {module:ol/source/State} [state] Source state.\n */\n\n\n/**\n * @classdesc\n * Base class for image sources where a canvas element is the image.\n * @api\n */\nvar ImageCanvasSource = (function (ImageSource) {\n  function ImageCanvasSource(options) {\n\n    ImageSource.call(this, {\n      attributions: options.attributions,\n      projection: options.projection,\n      resolutions: options.resolutions,\n      state: options.state\n    });\n\n    /**\n    * @private\n    * @type {module:ol/source/ImageCanvas~FunctionType}\n    */\n    this.canvasFunction_ = options.canvasFunction;\n\n    /**\n    * @private\n    * @type {module:ol/ImageCanvas}\n    */\n    this.canvas_ = null;\n\n    /**\n    * @private\n    * @type {number}\n    */\n    this.renderedRevision_ = 0;\n\n    /**\n    * @private\n    * @type {number}\n    */\n    this.ratio_ = options.ratio !== undefined ?\n      options.ratio : 1.5;\n\n  }\n\n  if ( ImageSource ) ImageCanvasSource.__proto__ = ImageSource;\n  ImageCanvasSource.prototype = Object.create( ImageSource && ImageSource.prototype );\n  ImageCanvasSource.prototype.constructor = ImageCanvasSource;\n\n  /**\n  * @inheritDoc\n  */\n  ImageCanvasSource.prototype.getImageInternal = function getImageInternal (extent, resolution, pixelRatio, projection) {\n    resolution = this.findNearestResolution(resolution);\n\n    var canvas = this.canvas_;\n    if (canvas &&\n       this.renderedRevision_ == this.getRevision() &&\n       canvas.getResolution() == resolution &&\n       canvas.getPixelRatio() == pixelRatio &&\n       containsExtent(canvas.getExtent(), extent)) {\n      return canvas;\n    }\n\n    extent = extent.slice();\n    scaleFromCenter(extent, this.ratio_);\n    var width = getWidth(extent) / resolution;\n    var height = getHeight(extent) / resolution;\n    var size = [width * pixelRatio, height * pixelRatio];\n\n    var canvasElement = this.canvasFunction_(\n      extent, resolution, pixelRatio, size, projection);\n    if (canvasElement) {\n      canvas = new ImageCanvas(extent, resolution, pixelRatio, canvasElement);\n    }\n    this.canvas_ = canvas;\n    this.renderedRevision_ = this.getRevision();\n\n    return canvas;\n  };\n\n  return ImageCanvasSource;\n}(ImageSource));\n\n\nexport default ImageCanvasSource;\n\n//# sourceMappingURL=ImageCanvas.js.map"},"lineCount":null}},"hash":"be49c4d06eada1238d758d7dbb4e2122","cacheData":{"env":{}}}